{
  "title": "Anang & Indri",
  "groom": {
    "name": "Iklas Anang Subekti",
    "parent": "Bpk Mukhammad Kadir & Ibu Rini"
  },
  "bride": {
    "name": "Indri Fauziah",
    "parent": "Bpk Ahmad Toha & Ibu Supraptiningsih"
  },
  "akad": {
    "date": "2027-10-14",
    "time": "08.00 WIB"
  },
  "resepsi": {
    "date": "2027-10-15",
    "time": "09.00 - Selesai"
  },
  "location": "Dk.Sabrang Balong 02/01 Ds.Gesikan Kab.Kebumen",
  "maps": "https://www.google.com/maps/embed?pb=!1m18!1m12!1m3!1d3021.9595375225967!2d109.688126!3d-7.7074592!2m3!1f0!2f0!3f0!3m2!1i1024!2i768!4f13.1!3m3!1m2!1s0x2e7ac9a3fd80dfe9%3A0xa525045ab8ee6fd7!2sToko%20Bunga%20MEKAR%20ABADI!5e1!3m2!1sid!2sid!4v1771903668213!5m2!1sid!2sid",
  "phone": "6283851284221",
  "quote": "...",
  "gallery": ["foto1.jpg", "foto2.jpg"],
  "qris": "qanang.jpeg" 
}
